setup.py
yconverter/__init__.py
yconverter/cli.py
yconverter/client.py
yconverter/models.py
yconverter/tests/__init__.py
yconverter/tests/test_client.py
yconverter/tests/test_init.py
yconverter-1.0.6.dist-info/LICENSE
yconverter-1.0.6.dist-info/METADATA
yconverter-1.0.6.dist-info/WHEEL
yconverter-1.0.6.dist-info/entry_points.txt
yconverter-1.0.6.dist-info/top_level.txt
yconverter-1.0.6.dist-info/RECORD
