Metadata-Version: 2.1
Name: yconverter
Version: 1.0.6
Summary: All fiat currency and crypto converter
Home-page: https://github.com/yedhrab/yConverter
Author: Yunus Emre Ak
Author-email: yemreak.com@gmail.com
License: Apache Software License 2.0
Project-URL: Changelog, https://github.com/yedhrab/YConverter/blob/main/CHANGELOG.md
Project-URL: Issue Tracker, https://github.com/yedhrab/YConverter/issues
Keywords: cryptocurrencyconverter,currencyconverter,converter,currecies,crpytocurrencies,cryptoconverter
Classifier: Development Status :: 5 - Production/Stable
Classifier: Intended Audience :: Developers
Classifier: License :: OSI Approved :: Apache Software License
Classifier: Operating System :: MacOS
Classifier: Operating System :: POSIX
Classifier: Operating System :: Unix
Classifier: Operating System :: Microsoft :: Windows
Classifier: Programming Language :: Python
Classifier: Programming Language :: Python :: 3.9
Classifier: Programming Language :: Python :: 3.10
Classifier: Programming Language :: Python :: Implementation :: CPython
Classifier: Programming Language :: Python :: Implementation :: PyPy
Classifier: Topic :: Utilities
Requires-Python: >=3.9
License-File: LICENSE
